wbwiki/__init__.py
wbwiki/admin.py
wbwiki/apps.py
wbwiki/dynamic_preferences_registry.py
wbwiki/factories.py
wbwiki/models.py
wbwiki/preferences.py
wbwiki/serializers.py
wbwiki/urls.py
wbwiki/migrations/0001_initial_squashed_0004_alter_wikiarticle_tags.py
wbwiki/migrations/0005_wikiarticlerelationship_and_more.py
wbwiki/migrations/0006_auto_20240103_0954.py
wbwiki/migrations/__init__.py
wbwiki/tests/__init__.py
wbwiki/tests/conftest.py
wbwiki/tests/signals.py
wbwiki/tests/test_initial.py
wbwiki/tests/tests.py
wbwiki/viewsets/__init__.py
wbwiki/viewsets/wikis.py
wbwiki/viewsets/buttons/__init__.py
wbwiki/viewsets/buttons/wikis.py
wbwiki/viewsets/display/__init__.py
wbwiki/viewsets/display/wikis.py
wbwiki/viewsets/endpoints/__init__.py
wbwiki/viewsets/endpoints/wikis.py
wbwiki/viewsets/menu/__init__.py
wbwiki/viewsets/menu/wikis.py
wbwiki/viewsets/preview/__init__.py
wbwiki/viewsets/titles/init.py
wbwiki-2.2.6.dist-info/METADATA
wbwiki-2.2.6.dist-info/WHEEL
wbwiki-2.2.6.dist-info/RECORD
