Metadata-Version: 2.4
Name: wbwiki
Version: 2.2.6
Author-email: Christopher Wittlinger <c.wittlinger@stainly.com>
Requires-Dist: wbcore
